{"prices":[{"id":1,"width":900,"height":2100,"loops_count":"0","materials":[{"id":12,"title":"\u041e\u043f\u0442","price":{"wholesale":10846,"dealer":14854,"retail":6150,"cost":5958}},{"id":13,"title":"\u0414\u0438\u043b\u0435\u0440","price":{"wholesale":11512,"dealer":6814,"retail":19352,"cost":13288}},{"id":14,"title":"\u0420\u043e\u0437\u043d\u0438\u0446\u0430","price":{"wholesale":1876,"dealer":5913,"retail":7646,"cost":9060}},{"id":15,"title":"\u0421\u0435\u0431\u0435\u0441\u0442\u043e\u0438\u043c\u043e\u0441\u0442\u044c","price":{"wholesale":15638,"dealer":10260,"retail":6300,"cost":5026}},{"id":16,"title":"\u041a\u043e\u044d\u0444\u0444\u0438\u0446\u0438\u0435\u043d\u0442","price":{"wholesale":7458,"dealer":2274,"retail":5741,"cost":1989}}]},{"id":12,"width":1000,"height":2100,"loops_count":"0","materials":[{"id":12,"title":"\u041e\u043f\u0442","price":{"wholesale":9739,"dealer":3680,"retail":1245,"cost":9037}},{"id":13,"title":"\u0414\u0438\u043b\u0435\u0440","price":{"wholesale":13990,"dealer":7126,"retail":15726,"cost":16428}},{"id":14,"title":"\u0420\u043e\u0437\u043d\u0438\u0446\u0430","price":{"wholesale":2706,"dealer":8148,"retail":7010,"cost":3929}},{"id":15,"title":"\u0421\u0435\u0431\u0435\u0441\u0442\u043e\u0438\u043c\u043e\u0441\u0442\u044c","price":{"wholesale":19334,"dealer":13378,"retail":15316,"cost":14874}},{"id":16,"title":"\u041a\u043e\u044d\u0444\u0444\u0438\u0446\u0438\u0435\u043d\u0442","price":{"wholesale":5331,"dealer":1981,"retail":7270,"cost":9235}}]},{"id":23,"width":800,"height":2300,"loops_count":"0","materials":[{"id":12,"title":"\u041e\u043f\u0442","price":{"wholesale":19096,"dealer":12610,"retail":18516,"cost":8114}},{"id":13,"title":"\u0414\u0438\u043b\u0435\u0440","price":{"wholesale":18962,"dealer":14070,"retail":11562,"cost":13866}},{"id":14,"title":"\u0420\u043e\u0437\u043d\u0438\u0446\u0430","price":{"wholesale":11548,"dealer":6520,"retail":8454,"cost":17482}},{"id":15,"title":"\u0421\u0435\u0431\u0435\u0441\u0442\u043e\u0438\u043c\u043e\u0441\u0442\u044c","price":{"wholesale":11952,"dealer":10348,"retail":15326,"cost":11210}},{"id":16,"title":"\u041a\u043e\u044d\u0444\u0444\u0438\u0446\u0438\u0435\u043d\u0442","price":{"wholesale":5610,"dealer":6547,"retail":1187,"cost":7606}}]},{"id":34,"width":900,"height":2300,"loops_count":"0","materials":[{"id":12,"title":"\u041e\u043f\u0442","price":{"wholesale":10846,"dealer":14854,"retail":6150,"cost":5958}},{"id":13,"title":"\u0414\u0438\u043b\u0435\u0440","price":{"wholesale":11512,"dealer":6814,"retail":19352,"cost":13288}},{"id":14,"title":"\u0420\u043e\u0437\u043d\u0438\u0446\u0430","price":{"wholesale":1876,"dealer":5913,"retail":7646,"cost":9060}},{"id":15,"title":"\u0421\u0435\u0431\u0435\u0441\u0442\u043e\u0438\u043c\u043e\u0441\u0442\u044c","price":{"wholesale":7819,"dealer":5130,"retail":3150,"cost":2513}},{"id":16,"title":"\u041a\u043e\u044d\u0444\u0444\u0438\u0446\u0438\u0435\u043d\u0442","price":{"wholesale":14916,"dealer":4548,"retail":11482,"cost":3978}}]},{"id":45,"width":1000,"height":2300,"loops_count":"0","materials":[{"id":12,"title":"\u041e\u043f\u0442","price":{"wholesale":9739,"dealer":3680,"retail":1245,"cost":9037}},{"id":13,"title":"\u0414\u0438\u043b\u0435\u0440","price":{"wholesale":6995,"dealer":3563,"retail":7863,"cost":8214}},{"id":14,"title":"\u0420\u043e\u0437\u043d\u0438\u0446\u0430","price":{"wholesale":5412,"dealer":16296,"retail":14020,"cost":7858}},{"id":15,"title":"\u0421\u0435\u0431\u0435\u0441\u0442\u043e\u0438\u043c\u043e\u0441\u0442\u044c","price":{"wholesale":9667,"dealer":6689,"retail":7658,"cost":7437}},{"id":16,"title":"\u041a\u043e\u044d\u0444\u0444\u0438\u0446\u0438\u0435\u043d\u0442","price":{"wholesale":10662,"dealer":3962,"retail":14540,"cost":18470}}]},{"id":56,"width":800,"height":2500,"loops_count":"0","materials":[{"id":12,"title":"\u041e\u043f\u0442","price":{"wholesale":19096,"dealer":12610,"retail":18516,"cost":8114}},{"id":13,"title":"\u0414\u0438\u043b\u0435\u0440","price":{"wholesale":9481,"dealer":7035,"retail":5781,"cost":6933}},{"id":14,"title":"\u0420\u043e\u0437\u043d\u0438\u0446\u0430","price":{"wholesale":5774,"dealer":3260,"retail":4227,"cost":8741}},{"id":15,"title":"\u0421\u0435\u0431\u0435\u0441\u0442\u043e\u0438\u043c\u043e\u0441\u0442\u044c","price":{"wholesale":11952,"dealer":10348,"retail":15326,"cost":11210}},{"id":16,"title":"\u041a\u043e\u044d\u0444\u0444\u0438\u0446\u0438\u0435\u043d\u0442","price":{"wholesale":5610,"dealer":6547,"retail":1187,"cost":7606}}]},{"id":67,"width":900,"height":2500,"loops_count":"0","materials":[{"id":12,"title":"\u041e\u043f\u0442","price":{"wholesale":10846,"dealer":14854,"retail":6150,"cost":5958}},{"id":13,"title":"\u0414\u0438\u043b\u0435\u0440","price":{"wholesale":11512,"dealer":6814,"retail":19352,"cost":13288}},{"id":14,"title":"\u0420\u043e\u0437\u043d\u0438\u0446\u0430","price":{"wholesale":1876,"dealer":5913,"retail":7646,"cost":9060}},{"id":15,"title":"\u0421\u0435\u0431\u0435\u0441\u0442\u043e\u0438\u043c\u043e\u0441\u0442\u044c","price":{"wholesale":7819,"dealer":5130,"retail":3150,"cost":2513}},{"id":16,"title":"\u041a\u043e\u044d\u0444\u0444\u0438\u0446\u0438\u0435\u043d\u0442","price":{"wholesale":7458,"dealer":2274,"retail":5741,"cost":1989}}]},{"id":78,"width":1000,"height":2500,"loops_count":"0","materials":[{"id":12,"title":"\u041e\u043f\u0442","price":{"wholesale":19478,"dealer":7360,"retail":2490,"cost":18074}},{"id":13,"title":"\u0414\u0438\u043b\u0435\u0440","price":{"wholesale":13990,"dealer":7126,"retail":15726,"cost":16428}},{"id":14,"title":"\u0420\u043e\u0437\u043d\u0438\u0446\u0430","price":{"wholesale":2706,"dealer":8148,"retail":7010,"cost":3929}},{"id":15,"title":"\u0421\u0435\u0431\u0435\u0441\u0442\u043e\u0438\u043c\u043e\u0441\u0442\u044c","price":{"wholesale":9667,"dealer":6689,"retail":7658,"cost":7437}},{"id":16,"title":"\u041a\u043e\u044d\u0444\u0444\u0438\u0446\u0438\u0435\u043d\u0442","price":{"wholesale":5331,"dealer":1981,"retail":7270,"cost":9235}}]},{"id":89,"width":800,"height":2700,"loops_count":"0","materials":[{"id":12,"title":"\u041e\u043f\u0442","price":{"wholesale":19096,"dealer":12610,"retail":18516,"cost":8114}},{"id":13,"title":"\u0414\u0438\u043b\u0435\u0440","price":{"wholesale":9481,"dealer":7035,"retail":5781,"cost":6933}},{"id":14,"title":"\u0420\u043e\u0437\u043d\u0438\u0446\u0430","price":{"wholesale":11548,"dealer":6520,"retail":8454,"cost":17482}},{"id":15,"title":"\u0421\u0435\u0431\u0435\u0441\u0442\u043e\u0438\u043c\u043e\u0441\u0442\u044c","price":{"wholesale":5976,"dealer":5174,"retail":7663,"cost":5605}},{"id":16,"title":"\u041a\u043e\u044d\u0444\u0444\u0438\u0446\u0438\u0435\u043d\u0442","price":{"wholesale":11220,"dealer":13094,"retail":2374,"cost":15212}}]},{"id":100,"width":900,"height":2700,"loops_count":"0","materials":[{"id":12,"title":"\u041e\u043f\u0442","price":{"wholesale":10846,"dealer":14854,"retail":6150,"cost":5958}},{"id":13,"title":"\u0414\u0438\u043b\u0435\u0440","price":{"wholesale":11512,"dealer":6814,"retail":19352,"cost":13288}},{"id":14,"title":"\u0420\u043e\u0437\u043d\u0438\u0446\u0430","price":{"wholesale":1876,"dealer":5913,"retail":7646,"cost":9060}},{"id":15,"title":"\u0421\u0435\u0431\u0435\u0441\u0442\u043e\u0438\u043c\u043e\u0441\u0442\u044c","price":{"wholesale":15638,"dealer":10260,"retail":6300,"cost":5026}},{"id":16,"title":"\u041a\u043e\u044d\u0444\u0444\u0438\u0446\u0438\u0435\u043d\u0442","price":{"wholesale":7458,"dealer":2274,"retail":5741,"cost":1989}}]},{"id":111,"width":1000,"height":2700,"loops_count":"0","materials":[{"id":12,"title":"\u041e\u043f\u0442","price":{"wholesale":19478,"dealer":7360,"retail":2490,"cost":18074}},{"id":13,"title":"\u0414\u0438\u043b\u0435\u0440","price":{"wholesale":6995,"dealer":3563,"retail":7863,"cost":8214}},{"id":14,"title":"\u0420\u043e\u0437\u043d\u0438\u0446\u0430","price":{"wholesale":5412,"dealer":16296,"retail":14020,"cost":7858}},{"id":15,"title":"\u0421\u0435\u0431\u0435\u0441\u0442\u043e\u0438\u043c\u043e\u0441\u0442\u044c","price":{"wholesale":19334,"dealer":13378,"retail":15316,"cost":14874}},{"id":16,"title":"\u041a\u043e\u044d\u0444\u0444\u0438\u0446\u0438\u0435\u043d\u0442","price":{"wholesale":10662,"dealer":3962,"retail":14540,"cost":18470}}]},{"id":122,"width":800,"height":2800,"loops_count":"0","materials":[{"id":12,"title":"\u041e\u043f\u0442","price":{"wholesale":19096,"dealer":12610,"retail":18516,"cost":8114}},{"id":13,"title":"\u0414\u0438\u043b\u0435\u0440","price":{"wholesale":9481,"dealer":7035,"retail":5781,"cost":6933}},{"id":14,"title":"\u0420\u043e\u0437\u043d\u0438\u0446\u0430","price":{"wholesale":11548,"dealer":6520,"retail":8454,"cost":17482}},{"id":15,"title":"\u0421\u0435\u0431\u0435\u0441\u0442\u043e\u0438\u043c\u043e\u0441\u0442\u044c","price":{"wholesale":5976,"dealer":5174,"retail":7663,"cost":5605}},{"id":16,"title":"\u041a\u043e\u044d\u0444\u0444\u0438\u0446\u0438\u0435\u043d\u0442","price":{"wholesale":11220,"dealer":13094,"retail":2374,"cost":15212}}]},{"id":133,"width":900,"height":2800,"loops_count":"0","materials":[{"id":12,"title":"\u041e\u043f\u0442","price":{"wholesale":10846,"dealer":14854,"retail":6150,"cost":5958}},{"id":13,"title":"\u0414\u0438\u043b\u0435\u0440","price":{"wholesale":11512,"dealer":6814,"retail":19352,"cost":13288}},{"id":14,"title":"\u0420\u043e\u0437\u043d\u0438\u0446\u0430","price":{"wholesale":3752,"dealer":11826,"retail":15292,"cost":18120}},{"id":15,"title":"\u0421\u0435\u0431\u0435\u0441\u0442\u043e\u0438\u043c\u043e\u0441\u0442\u044c","price":{"wholesale":7819,"dealer":5130,"retail":3150,"cost":2513}},{"id":16,"title":"\u041a\u043e\u044d\u0444\u0444\u0438\u0446\u0438\u0435\u043d\u0442","price":{"wholesale":7458,"dealer":2274,"retail":5741,"cost":1989}}]},{"id":144,"width":1000,"height":2800,"loops_count":"0","materials":[{"id":12,"title":"\u041e\u043f\u0442","price":{"wholesale":19478,"dealer":7360,"retail":2490,"cost":18074}},{"id":13,"title":"\u0414\u0438\u043b\u0435\u0440","price":{"wholesale":6995,"dealer":3563,"retail":7863,"cost":8214}},{"id":14,"title":"\u0420\u043e\u0437\u043d\u0438\u0446\u0430","price":{"wholesale":2706,"dealer":8148,"retail":7010,"cost":3929}},{"id":15,"title":"\u0421\u0435\u0431\u0435\u0441\u0442\u043e\u0438\u043c\u043e\u0441\u0442\u044c","price":{"wholesale":19334,"dealer":13378,"retail":15316,"cost":14874}},{"id":16,"title":"\u041a\u043e\u044d\u0444\u0444\u0438\u0446\u0438\u0435\u043d\u0442","price":{"wholesale":10662,"dealer":3962,"retail":14540,"cost":18470}}]},{"id":155,"width":800,"height":3000,"loops_count":"0","materials":[{"id":12,"title":"\u041e\u043f\u0442","price":{"wholesale":19096,"dealer":12610,"retail":18516,"cost":8114}},{"id":13,"title":"\u0414\u0438\u043b\u0435\u0440","price":{"wholesale":9481,"dealer":7035,"retail":5781,"cost":6933}},{"id":14,"title":"\u0420\u043e\u0437\u043d\u0438\u0446\u0430","price":{"wholesale":5774,"dealer":3260,"retail":4227,"cost":8741}},{"id":15,"title":"\u0421\u0435\u0431\u0435\u0441\u0442\u043e\u0438\u043c\u043e\u0441\u0442\u044c","price":{"wholesale":5976,"dealer":5174,"retail":7663,"cost":5605}},{"id":16,"title":"\u041a\u043e\u044d\u0444\u0444\u0438\u0446\u0438\u0435\u043d\u0442","price":{"wholesale":5610,"dealer":6547,"retail":1187,"cost":7606}}]},{"id":166,"width":900,"height":3000,"loops_count":"0","materials":[{"id":12,"title":"\u041e\u043f\u0442","price":{"wholesale":10846,"dealer":14854,"retail":6150,"cost":5958}},{"id":13,"title":"\u0414\u0438\u043b\u0435\u0440","price":{"wholesale":5756,"dealer":3407,"retail":9676,"cost":6644}},{"id":14,"title":"\u0420\u043e\u0437\u043d\u0438\u0446\u0430","price":{"wholesale":3752,"dealer":11826,"retail":15292,"cost":18120}},{"id":15,"title":"\u0421\u0435\u0431\u0435\u0441\u0442\u043e\u0438\u043c\u043e\u0441\u0442\u044c","price":{"wholesale":7819,"dealer":5130,"retail":3150,"cost":2513}},{"id":16,"title":"\u041a\u043e\u044d\u0444\u0444\u0438\u0446\u0438\u0435\u043d\u0442","price":{"wholesale":14916,"dealer":4548,"retail":11482,"cost":3978}}]},{"id":177,"width":1000,"height":3000,"loops_count":"0","materials":[{"id":12,"title":"\u041e\u043f\u0442","price":{"wholesale":19478,"dealer":7360,"retail":2490,"cost":18074}},{"id":13,"title":"\u0414\u0438\u043b\u0435\u0440","price":{"wholesale":13990,"dealer":7126,"retail":15726,"cost":16428}},{"id":14,"title":"\u0420\u043e\u0437\u043d\u0438\u0446\u0430","price":{"wholesale":5412,"dealer":16296,"retail":14020,"cost":7858}},{"id":15,"title":"\u0421\u0435\u0431\u0435\u0441\u0442\u043e\u0438\u043c\u043e\u0441\u0442\u044c","price":{"wholesale":9667,"dealer":6689,"retail":7658,"cost":7437}},{"id":16,"title":"\u041a\u043e\u044d\u0444\u0444\u0438\u0446\u0438\u0435\u043d\u0442","price":{"wholesale":10662,"dealer":3962,"retail":14540,"cost":18470}}]},{"id":188,"width":800,"height":3500,"loops_count":"0","materials":[{"id":12,"title":"\u041e\u043f\u0442","price":{"wholesale":19096,"dealer":12610,"retail":18516,"cost":8114}},{"id":13,"title":"\u0414\u0438\u043b\u0435\u0440","price":{"wholesale":9481,"dealer":7035,"retail":5781,"cost":6933}},{"id":14,"title":"\u0420\u043e\u0437\u043d\u0438\u0446\u0430","price":{"wholesale":11548,"dealer":6520,"retail":8454,"cost":17482}},{"id":15,"title":"\u0421\u0435\u0431\u0435\u0441\u0442\u043e\u0438\u043c\u043e\u0441\u0442\u044c","price":{"wholesale":11952,"dealer":10348,"retail":15326,"cost":11210}},{"id":16,"title":"\u041a\u043e\u044d\u0444\u0444\u0438\u0446\u0438\u0435\u043d\u0442","price":{"wholesale":5610,"dealer":6547,"retail":1187,"cost":7606}}]},{"id":199,"width":900,"height":3500,"loops_count":"0","materials":[{"id":12,"title":"\u041e\u043f\u0442","price":{"wholesale":5423,"dealer":7427,"retail":3075,"cost":2979}},{"id":13,"title":"\u0414\u0438\u043b\u0435\u0440","price":{"wholesale":11512,"dealer":6814,"retail":19352,"cost":13288}},{"id":14,"title":"\u0420\u043e\u0437\u043d\u0438\u0446\u0430","price":{"wholesale":1876,"dealer":5913,"retail":7646,"cost":9060}},{"id":15,"title":"\u0421\u0435\u0431\u0435\u0441\u0442\u043e\u0438\u043c\u043e\u0441\u0442\u044c","price":{"wholesale":15638,"dealer":10260,"retail":6300,"cost":5026}},{"id":16,"title":"\u041a\u043e\u044d\u0444\u0444\u0438\u0446\u0438\u0435\u043d\u0442","price":{"wholesale":14916,"dealer":4548,"retail":11482,"cost":3978}}]},{"id":210,"width":1000,"height":3500,"loops_count":"0","materials":[{"id":12,"title":"\u041e\u043f\u0442","price":{"wholesale":19478,"dealer":7360,"retail":2490,"cost":18074}},{"id":13,"title":"\u0414\u0438\u043b\u0435\u0440","price":{"wholesale":13990,"dealer":7126,"retail":15726,"cost":16428}},{"id":14,"title":"\u0420\u043e\u0437\u043d\u0438\u0446\u0430","price":{"wholesale":5412,"dealer":16296,"retail":14020,"cost":7858}},{"id":15,"title":"\u0421\u0435\u0431\u0435\u0441\u0442\u043e\u0438\u043c\u043e\u0441\u0442\u044c","price":{"wholesale":9667,"dealer":6689,"retail":7658,"cost":7437}},{"id":16,"title":"\u041a\u043e\u044d\u0444\u0444\u0438\u0446\u0438\u0435\u043d\u0442","price":{"wholesale":10662,"dealer":3962,"retail":14540,"cost":18470}}]},{"id":221,"width":800,"height":4000,"loops_count":"0","materials":[{"id":12,"title":"\u041e\u043f\u0442","price":{"wholesale":9548,"dealer":6305,"retail":9258,"cost":4057}},{"id":13,"title":"\u0414\u0438\u043b\u0435\u0440","price":{"wholesale":9481,"dealer":7035,"retail":5781,"cost":6933}},{"id":14,"title":"\u0420\u043e\u0437\u043d\u0438\u0446\u0430","price":{"wholesale":5774,"dealer":3260,"retail":4227,"cost":8741}},{"id":15,"title":"\u0421\u0435\u0431\u0435\u0441\u0442\u043e\u0438\u043c\u043e\u0441\u0442\u044c","price":{"wholesale":11952,"dealer":10348,"retail":15326,"cost":11210}},{"id":16,"title":"\u041a\u043e\u044d\u0444\u0444\u0438\u0446\u0438\u0435\u043d\u0442","price":{"wholesale":11220,"dealer":13094,"retail":2374,"cost":15212}}]},{"id":232,"width":900,"height":4000,"loops_count":"0","materials":[{"id":12,"title":"\u041e\u043f\u0442","price":{"wholesale":5423,"dealer":7427,"retail":3075,"cost":2979}},{"id":13,"title":"\u0414\u0438\u043b\u0435\u0440","price":{"wholesale":5756,"dealer":3407,"retail":9676,"cost":6644}},{"id":14,"title":"\u0420\u043e\u0437\u043d\u0438\u0446\u0430","price":{"wholesale":3752,"dealer":11826,"retail":15292,"cost":18120}},{"id":15,"title":"\u0421\u0435\u0431\u0435\u0441\u0442\u043e\u0438\u043c\u043e\u0441\u0442\u044c","price":{"wholesale":15638,"dealer":10260,"retail":6300,"cost":5026}},{"id":16,"title":"\u041a\u043e\u044d\u0444\u0444\u0438\u0446\u0438\u0435\u043d\u0442","price":{"wholesale":14916,"dealer":4548,"retail":11482,"cost":3978}}]},{"id":243,"width":1000,"height":4000,"loops_count":"0","materials":[{"id":12,"title":"\u041e\u043f\u0442","price":{"wholesale":9739,"dealer":3680,"retail":1245,"cost":9037}},{"id":13,"title":"\u0414\u0438\u043b\u0435\u0440","price":{"wholesale":13990,"dealer":7126,"retail":15726,"cost":16428}},{"id":14,"title":"\u0420\u043e\u0437\u043d\u0438\u0446\u0430","price":{"wholesale":5412,"dealer":16296,"retail":14020,"cost":7858}},{"id":15,"title":"\u0421\u0435\u0431\u0435\u0441\u0442\u043e\u0438\u043c\u043e\u0441\u0442\u044c","price":{"wholesale":19334,"dealer":13378,"retail":15316,"cost":14874}},{"id":16,"title":"\u041a\u043e\u044d\u0444\u0444\u0438\u0446\u0438\u0435\u043d\u0442","price":{"wholesale":10662,"dealer":3962,"retail":14540,"cost":18470}}]}],"depth":{"-":[{"width":900,"height":2100,"price":{"wholesale":2471,"dealer":5694,"retail":7801,"cost":4370}},{"width":900,"height":2100,"price":{"wholesale":4942,"dealer":11388,"retail":15602,"cost":8740}},{"width":1000,"height":2100,"price":{"wholesale":16922,"dealer":9506,"retail":15756,"cost":7750}},{"width":1000,"height":2100,"price":{"wholesale":16922,"dealer":9506,"retail":15756,"cost":7750}},{"width":800,"height":2300,"price":{"wholesale":8150,"dealer":13090,"retail":18070,"cost":19076}},{"width":800,"height":2300,"price":{"wholesale":4075,"dealer":6545,"retail":9035,"cost":9538}},{"width":900,"height":2300,"price":{"wholesale":4942,"dealer":11388,"retail":15602,"cost":8740}},{"width":900,"height":2300,"price":{"wholesale":4942,"dealer":11388,"retail":15602,"cost":8740}},{"width":1000,"height":2300,"price":{"wholesale":8461,"dealer":4753,"retail":7878,"cost":3875}},{"width":1000,"height":2300,"price":{"wholesale":16922,"dealer":9506,"retail":15756,"cost":7750}},{"width":800,"height":2500,"price":{"wholesale":8150,"dealer":13090,"retail":18070,"cost":19076}},{"width":800,"height":2500,"price":{"wholesale":4075,"dealer":6545,"retail":9035,"cost":9538}},{"width":900,"height":2500,"price":{"wholesale":2471,"dealer":5694,"retail":7801,"cost":4370}},{"width":900,"height":2500,"price":{"wholesale":4942,"dealer":11388,"retail":15602,"cost":8740}},{"width":1000,"height":2500,"price":{"wholesale":16922,"dealer":9506,"retail":15756,"cost":7750}},{"width":1000,"height":2500,"price":{"wholesale":16922,"dealer":9506,"retail":15756,"cost":7750}},{"width":800,"height":2700,"price":{"wholesale":8150,"dealer":13090,"retail":18070,"cost":19076}},{"width":800,"height":2700,"price":{"wholesale":4075,"dealer":6545,"retail":9035,"cost":9538}},{"width":900,"height":2700,"price":{"wholesale":4942,"dealer":11388,"retail":15602,"cost":8740}},{"width":900,"height":2700,"price":{"wholesale":2471,"dealer":5694,"retail":7801,"cost":4370}},{"width":1000,"height":2700,"price":{"wholesale":16922,"dealer":9506,"retail":15756,"cost":7750}},{"width":1000,"height":2700,"price":{"wholesale":8461,"dealer":4753,"retail":7878,"cost":3875}},{"width":800,"height":2800,"price":{"wholesale":8150,"dealer":13090,"retail":18070,"cost":19076}},{"width":800,"height":2800,"price":{"wholesale":4075,"dealer":6545,"retail":9035,"cost":9538}},{"width":900,"height":2800,"price":{"wholesale":2471,"dealer":5694,"retail":7801,"cost":4370}},{"width":900,"height":2800,"price":{"wholesale":4942,"dealer":11388,"retail":15602,"cost":8740}},{"width":1000,"height":2800,"price":{"wholesale":16922,"dealer":9506,"retail":15756,"cost":7750}},{"width":1000,"height":2800,"price":{"wholesale":8461,"dealer":4753,"retail":7878,"cost":3875}},{"width":800,"height":3000,"price":{"wholesale":4075,"dealer":6545,"retail":9035,"cost":9538}},{"width":800,"height":3000,"price":{"wholesale":8150,"dealer":13090,"retail":18070,"cost":19076}},{"width":900,"height":3000,"price":{"wholesale":2471,"dealer":5694,"retail":7801,"cost":4370}},{"width":900,"height":3000,"price":{"wholesale":2471,"dealer":5694,"retail":7801,"cost":4370}},{"width":1000,"height":3000,"price":{"wholesale":16922,"dealer":9506,"retail":15756,"cost":7750}},{"width":1000,"height":3000,"price":{"wholesale":16922,"dealer":9506,"retail":15756,"cost":7750}},{"width":800,"height":3500,"price":{"wholesale":4075,"dealer":6545,"retail":9035,"cost":9538}},{"width":800,"height":3500,"price":{"wholesale":4075,"dealer":6545,"retail":9035,"cost":9538}},{"width":900,"height":3500,"price":{"wholesale":4942,"dealer":11388,"retail":15602,"cost":8740}},{"width":900,"height":3500,"price":{"wholesale":2471,"dealer":5694,"retail":7801,"cost":4370}},{"width":1000,"height":3500,"price":{"wholesale":16922,"dealer":9506,"retail":15756,"cost":7750}},{"width":1000,"height":3500,"price":{"wholesale":8461,"dealer":4753,"retail":7878,"cost":3875}},{"width":800,"height":4000,"price":{"wholesale":4075,"dealer":6545,"retail":9035,"cost":9538}},{"width":800,"height":4000,"price":{"wholesale":4075,"dealer":6545,"retail":9035,"cost":9538}},{"width":900,"height":4000,"price":{"wholesale":4942,"dealer":11388,"retail":15602,"cost":8740}},{"width":900,"height":4000,"price":{"wholesale":2471,"dealer":5694,"retail":7801,"cost":4370}},{"width":1000,"height":4000,"price":{"wholesale":16922,"dealer":9506,"retail":15756,"cost":7750}},{"width":1000,"height":4000,"price":{"wholesale":8461,"dealer":4753,"retail":7878,"cost":3875}}]},"materials":[{"id":1,"title":"\u041f\u043e\u0434 \u043f\u043e\u043a\u0440\u0430\u0441\u043a\u0443","order_position":0,"wrapper_variants":[{"uuid":"ae8de4f3-b42c-49bd-83b5-18b02f9ae51d","image":"https:\/\/via.placeholder.com\/640x480.png\/003388?text=vitae","title":"Necessitatibus saepe ut optio reprehenderit.","description":"Recusandae et illum ea sint at deserunt."},{"uuid":"6ea5c835-bc06-46fc-9ab4-0635b25068d4","image":"https:\/\/via.placeholder.com\/640x480.png\/0066cc?text=et","title":"Optio asperiores culpa dolorem quo.","description":"Et ratione velit accusamus a saepe enim eos."},{"uuid":"628e7ad5-4ce4-4d85-ad41-b6945dc4eb81","image":"https:\/\/via.placeholder.com\/640x480.png\/00cccc?text=accusamus","title":"Quis impedit ut non quia.","description":"Cumque nobis qui odio sequi animi facere facere."},{"uuid":"9169141f-d52f-4e6f-b4df-84e49153db61","image":"https:\/\/via.placeholder.com\/640x480.png\/0022dd?text=velit","title":"Deserunt earum et eius quia neque.","description":"Doloremque voluptatem numquam quia cumque eos."},{"uuid":"df897445-3267-4b24-b2d7-8544a8deecee","image":"https:\/\/via.placeholder.com\/640x480.png\/000088?text=laborum","title":"Vel rem illo laborum odit mollitia.","description":"Qui eos et soluta occaecati dolorem quibusdam."},{"uuid":"5c66e850-3f57-4f3e-986f-c2b599de14be","image":"https:\/\/via.placeholder.com\/640x480.png\/000055?text=et","title":"Vitae ex maiores est maxime nesciunt magnam aut.","description":"Est ea ipsam quas."},{"uuid":"20a01951-2e29-459b-838f-357763066639","image":"https:\/\/via.placeholder.com\/640x480.png\/001177?text=ducimus","title":"Maiores nihil ad autem ducimus sit aut.","description":"Mollitia reiciendis dolorem sint."},{"uuid":"596d6eda-f6da-4752-b4e5-bce5ec13e69f","image":"https:\/\/via.placeholder.com\/640x480.png\/007700?text=suscipit","title":"Eius aliquid distinctio impedit.","description":"Eaque consequatur eos natus ducimus sed unde."},{"uuid":"900fce8e-8837-4122-8165-f059b79260e9","image":"https:\/\/via.placeholder.com\/640x480.png\/0066bb?text=omnis","title":"Laboriosam quasi quae autem eum.","description":"Minus qui et asperiores fugiat praesentium."},{"uuid":"ea0ee597-4c32-4fee-8707-ed28690668ec","image":"https:\/\/via.placeholder.com\/640x480.png\/0088dd?text=eligendi","title":"Labore dicta voluptas perspiciatis libero.","description":"Reiciendis asperiores animi labore iure."}],"door_variants":[{"uuid":"97968a8a-bcca-481d-ae1e-fb1b5d6f68be","image":"https:\/\/via.placeholder.com\/640x480.png\/00eeaa?text=est","title":"Quos voluptatem eaque cumque magnam aperiam.","description":"Quisquam non minima quia dolore ut deleniti qui."},{"uuid":"2ecbb3cc-27b7-4a1f-bcdb-8fbad00d73c0","image":"https:\/\/via.placeholder.com\/640x480.png\/00bbaa?text=tempore","title":"Esse minima voluptas ad corporis aliquam.","description":"Tempore quasi perferendis qui dolores voluptatem."},{"uuid":"5887a9a6-3be0-4d05-8a65-f064080b2a54","image":"https:\/\/via.placeholder.com\/640x480.png\/007755?text=ipsam","title":"Quia voluptas eum non enim ut.","description":"Reiciendis dolor incidunt iste sint sit est."},{"uuid":"e1622b0d-ecb7-4fb6-9611-0521572e4817","image":"https:\/\/via.placeholder.com\/640x480.png\/00aacc?text=officiis","title":"Dolores quia enim dolor praesentium earum.","description":"Porro laborum at ea assumenda iste est."},{"uuid":"10ad1259-0951-4e36-8e68-d401877c9aee","image":"https:\/\/via.placeholder.com\/640x480.png\/00aaaa?text=fugiat","title":"Cumque deleniti fugit ut tenetur pariatur.","description":"Iusto omnis quas velit nulla provident nihil."},{"uuid":"d7b0e444-3ca2-4b29-9f92-2a35fb468015","image":"https:\/\/via.placeholder.com\/640x480.png\/0088aa?text=et","title":"Ducimus hic animi est soluta.","description":"Voluptate ad facilis sit dolores quasi."},{"uuid":"32ed641a-0bec-400c-b87b-5d7c2c869984","image":"https:\/\/via.placeholder.com\/640x480.png\/005588?text=accusantium","title":"Id quo repudiandae excepturi ab minus aperiam.","description":"Ut ea illo aut maiores voluptatem."},{"uuid":"3dd65c8c-f3b3-4486-9f25-84eed8d5b93a","image":"https:\/\/via.placeholder.com\/640x480.png\/00eedd?text=qui","title":"Rerum labore voluptate sit nisi.","description":"Voluptatem aliquid id aut et nobis debitis."}],"created_at":"2024-06-27T19:09:49.000000Z","updated_at":"2024-06-27 19:09:49"},{"id":2,"title":"\u0421\u0442\u0435\u043a\u043b\u043e \u043a\u0440\u0430\u0448\u0435\u043d\u043d\u043e\u0435","order_position":0,"wrapper_variants":[{"uuid":"c8a97bed-d53d-423c-9b89-8fdee19d5fd0","image":"https:\/\/via.placeholder.com\/640x480.png\/004477?text=eum","title":"Ut est aliquid ab et molestias blanditiis.","description":"Magni accusantium autem possimus inventore iste."},{"uuid":"d6354b27-bcb3-416f-af60-a84668d955cc","image":"https:\/\/via.placeholder.com\/640x480.png\/002200?text=quis","title":"Et optio nihil blanditiis rem dolore ut sapiente.","description":"Eaque culpa reiciendis sit."},{"uuid":"549d91c5-f3fe-4561-a6db-746bb5b07db8","image":"https:\/\/via.placeholder.com\/640x480.png\/009977?text=ipsum","title":"Vitae qui sapiente modi. Aliquam ut sed sunt.","description":"Odio odio maiores officia reprehenderit."},{"uuid":"b530f4e0-6da9-43ff-a241-e27f52319698","image":"https:\/\/via.placeholder.com\/640x480.png\/0033cc?text=qui","title":"Ratione doloremque provident velit.","description":"Animi autem quod nulla dolores nihil placeat."},{"uuid":"fe08d2f5-59b4-46e9-b644-17c5bf658ae0","image":"https:\/\/via.placeholder.com\/640x480.png\/0055aa?text=quidem","title":"Et qui voluptas debitis quaerat error quia.","description":"Quisquam qui dolorum alias in quis enim."},{"uuid":"30d27506-fcfe-4d09-8c76-4d3bf8ae4e5e","image":"https:\/\/via.placeholder.com\/640x480.png\/00aa77?text=at","title":"Atque quaerat enim maiores sint veniam suscipit.","description":"Eligendi id minus sint sed architecto."}],"door_variants":[{"uuid":"644070e3-2c83-4e4a-acd0-6d14166be714","image":"https:\/\/via.placeholder.com\/640x480.png\/00aa33?text=odio","title":"Quos autem nisi quia quia a maiores cum.","description":"Eligendi et consequuntur nostrum."},{"uuid":"976be78b-8bdb-4368-9683-8caa39ef65b3","image":"https:\/\/via.placeholder.com\/640x480.png\/0055bb?text=reprehenderit","title":"Provident commodi qui veritatis dolores dicta.","description":"Doloremque rerum commodi aut adipisci accusamus."},{"uuid":"1bcf50eb-8543-42ca-b673-b88a6584f1b2","image":"https:\/\/via.placeholder.com\/640x480.png\/00cccc?text=alias","title":"Et quis consectetur doloribus facilis hic quam.","description":"Vel fugit pariatur itaque saepe vitae."},{"uuid":"d980a5f3-af04-4aaa-ba5b-71828c139194","image":"https:\/\/via.placeholder.com\/640x480.png\/000011?text=quis","title":"Accusamus qui tenetur qui maiores accusamus.","description":"Vitae sunt facere et maiores sint voluptas."},{"uuid":"26d25a65-881b-4a1a-8eda-b1f6b4b3b1f0","image":"https:\/\/via.placeholder.com\/640x480.png\/007722?text=fuga","title":"Dolor rerum dolorem praesentium.","description":"At nostrum reiciendis id molestiae."},{"uuid":"6e6d4db2-00f8-4ff0-8973-cb926a7cb7c8","image":"https:\/\/via.placeholder.com\/640x480.png\/000033?text=quae","title":"In aut non id qui. Non error qui omnis ratione.","description":"Nulla ea unde nulla quo nisi accusantium."},{"uuid":"8e8ef6f6-942d-4bde-8633-e27bda640601","image":"https:\/\/via.placeholder.com\/640x480.png\/009988?text=sed","title":"Iste quis eos hic veniam natus ipsum.","description":"Dolorem aut aut iusto ab sit sint laudantium sed."}],"created_at":"2024-06-27T19:09:49.000000Z","updated_at":"2024-06-27 19:09:49"},{"id":3,"title":"\u0417\u0435\u0440\u043a\u0430\u043b\u043e","order_position":0,"wrapper_variants":[{"uuid":"ab1ce09a-e444-4560-8cd4-906b0a2b63a1","image":"https:\/\/via.placeholder.com\/640x480.png\/003377?text=dolore","title":"Perferendis modi perspiciatis vel delectus enim.","description":"Quos sint quis qui vel nulla."},{"uuid":"3a05e22e-e640-42cd-8e85-6011ae9053d5","image":"https:\/\/via.placeholder.com\/640x480.png\/00ee22?text=atque","title":"Itaque ullam illo excepturi ea animi.","description":"Nisi nihil vel dolores iste natus."},{"uuid":"57868d44-c847-4454-8ff2-8b3b94ab1dc2","image":"https:\/\/via.placeholder.com\/640x480.png\/007711?text=maxime","title":"Et atque autem doloribus ut impedit commodi.","description":"Dolore repudiandae odio aut repellendus."},{"uuid":"950e6456-9cee-4c47-bca5-a60344488d0e","image":"https:\/\/via.placeholder.com\/640x480.png\/0011ff?text=rerum","title":"A nisi voluptatibus fugit.","description":"Est repudiandae reprehenderit ut qui voluptate."},{"uuid":"5c58a138-6039-4c58-900e-aecf9757c5f3","image":"https:\/\/via.placeholder.com\/640x480.png\/00aaee?text=quaerat","title":"Vel est et ad sapiente.","description":"Adipisci officia animi aut aperiam."},{"uuid":"95f67af7-9ee6-493a-8715-7d01211a2b26","image":"https:\/\/via.placeholder.com\/640x480.png\/002222?text=et","title":"Vel ea maiores accusantium.","description":"Reprehenderit sit numquam enim."},{"uuid":"0a9f1d22-4488-4035-ab08-9e680779a09e","image":"https:\/\/via.placeholder.com\/640x480.png\/007722?text=voluptatem","title":"Id quo eos magni tempore.","description":"Ut iure modi enim tempore rem magnam."},{"uuid":"9be79a3c-9ca4-458b-a530-35247e7a160d","image":"https:\/\/via.placeholder.com\/640x480.png\/0099aa?text=nam","title":"Reprehenderit qui quo omnis sint.","description":"Eum aspernatur mollitia rerum quos."},{"uuid":"bd49209f-5005-4fc1-8bc8-b4f4dad5f625","image":"https:\/\/via.placeholder.com\/640x480.png\/00ee44?text=ea","title":"Et qui nobis est et.","description":"Officia nemo ab occaecati."},{"uuid":"e59d68a7-0820-4303-a059-1fa4c862b5d7","image":"https:\/\/via.placeholder.com\/640x480.png\/007711?text=occaecati","title":"Delectus accusantium sit sit delectus quae.","description":"Deleniti dolorem aut quisquam dolores."}],"door_variants":[{"uuid":"0872f29c-80f2-4b1b-9a0a-8e2a0397eacb","image":"https:\/\/via.placeholder.com\/640x480.png\/00aadd?text=laudantium","title":"Vel ut beatae labore ut earum.","description":"Veniam corrupti harum odio in inventore."},{"uuid":"dd7f1b54-9261-4e19-9b40-effb6a13bfbd","image":"https:\/\/via.placeholder.com\/640x480.png\/00ee00?text=beatae","title":"Ipsam minus suscipit error est ea qui.","description":"Occaecati rerum doloremque quod odio."},{"uuid":"2f9efc64-d523-4ebe-b61f-ea3cd7907604","image":"https:\/\/via.placeholder.com\/640x480.png\/0033ee?text=veritatis","title":"Sit maiores et quasi fugiat odit nihil quo.","description":"Quidem iste alias aut libero reprehenderit aut."},{"uuid":"bb1145ed-0f03-412d-9647-8a421cffda2a","image":"https:\/\/via.placeholder.com\/640x480.png\/00ffcc?text=ea","title":"Tempora deleniti nihil cum aut eum.","description":"Qui dolor ratione error ex laborum accusamus."},{"uuid":"903b0d6a-566a-4851-852a-9b3571c994f9","image":"https:\/\/via.placeholder.com\/640x480.png\/001122?text=omnis","title":"Sed natus quam rem. Cupiditate maiores optio id.","description":"Voluptas aperiam dolorum est qui doloribus sequi."},{"uuid":"b7a45302-688b-4bc0-b338-1ab1da3b2b92","image":"https:\/\/via.placeholder.com\/640x480.png\/00ee99?text=labore","title":"Laborum reprehenderit id vel impedit dicta.","description":"Quia unde similique tenetur quia."},{"uuid":"ba26de17-360b-447e-93f5-61dd2eb2ecf6","image":"https:\/\/via.placeholder.com\/640x480.png\/0088bb?text=possimus","title":"Dicta est non et rem.","description":"Expedita magnam minima beatae corporis."}],"created_at":"2024-06-27T19:09:49.000000Z","updated_at":"2024-06-27 19:09:49"},{"id":4,"title":"\u0421\u0442\u0435\u043a\u043b\u043e \u0446\u0432\u0435\u0442\u043d\u043e\u0435(\u041b\u0430\u043a\u043e\u0431\u0435\u043b\u044c)","order_position":0,"wrapper_variants":[{"uuid":"6f160f04-67ef-4811-ba7d-f2892776a57c","image":"https:\/\/via.placeholder.com\/640x480.png\/007777?text=consequatur","title":"Velit nam ut eos rerum expedita neque.","description":"Non illo dolores quia. Ab qui optio tenetur."},{"uuid":"74c3194b-2bdd-42c3-8017-c61386505254","image":"https:\/\/via.placeholder.com\/640x480.png\/00ccbb?text=cupiditate","title":"Non aperiam dicta quia.","description":"Nulla et dolor voluptas amet ullam sit."},{"uuid":"bdd8a9cc-7144-4af6-8f9d-b1ef4d15704e","image":"https:\/\/via.placeholder.com\/640x480.png\/001144?text=rerum","title":"Est officiis adipisci omnis facere qui.","description":"Fuga consequatur saepe dolor omnis et."},{"uuid":"8870c123-817e-459b-8da3-082084210fa2","image":"https:\/\/via.placeholder.com\/640x480.png\/00bb77?text=ea","title":"Omnis aperiam soluta eius sit consequatur.","description":"Dolores ab doloremque ratione eos."},{"uuid":"7fcc49c2-0145-429d-868a-46402e566144","image":"https:\/\/via.placeholder.com\/640x480.png\/00aa77?text=eius","title":"Asperiores quia dolor qui saepe architecto ipsam.","description":"Explicabo dicta corporis labore voluptatem."},{"uuid":"c52fac85-3696-4cb4-bcb8-8758a42629bf","image":"https:\/\/via.placeholder.com\/640x480.png\/003311?text=explicabo","title":"Nemo rem esse deleniti at est dolore.","description":"Asperiores error dolore sed ipsam."},{"uuid":"7c5c4979-a4f2-4867-a5a4-865f24e33167","image":"https:\/\/via.placeholder.com\/640x480.png\/002266?text=sit","title":"Ipsam aliquam accusantium voluptas.","description":"Autem eaque voluptatem optio eum."}],"door_variants":[{"uuid":"28bd10b8-ee8c-40f6-b31e-c1cc7275aed5","image":"https:\/\/via.placeholder.com\/640x480.png\/00ff22?text=beatae","title":"Temporibus numquam facilis ea minima.","description":"Ea debitis dolore sint repellat quaerat tempora."},{"uuid":"66003e81-1f9b-40a4-b881-59875f59a8e3","image":"https:\/\/via.placeholder.com\/640x480.png\/0088ff?text=est","title":"Omnis totam debitis voluptates sint sed.","description":"Et est ea est qui molestiae."},{"uuid":"6be5c22c-36ac-47d4-ab25-a42594590340","image":"https:\/\/via.placeholder.com\/640x480.png\/00ee77?text=molestiae","title":"Doloribus asperiores et enim et.","description":"Esse assumenda delectus est sed consequuntur."},{"uuid":"4dd2f174-3685-47be-95ee-ff2bb3fa44f1","image":"https:\/\/via.placeholder.com\/640x480.png\/0099cc?text=mollitia","title":"Vel aut corrupti perferendis eius.","description":"Quam a rerum voluptatem et vitae."},{"uuid":"4402d9b7-6daf-4a0c-92e7-95c965e5486a","image":"https:\/\/via.placeholder.com\/640x480.png\/0011bb?text=molestias","title":"Accusantium et neque aliquam alias.","description":"Id magni aperiam tenetur similique."},{"uuid":"26b2743f-f4bd-49ed-add7-3d3342d8ccce","image":"https:\/\/via.placeholder.com\/640x480.png\/005500?text=dolores","title":"Sint et libero pariatur deserunt ut sit et.","description":"Non necessitatibus a eum et."},{"uuid":"11d90a75-82c1-4fb3-a597-4c3e176023b8","image":"https:\/\/via.placeholder.com\/640x480.png\/00bbaa?text=doloribus","title":"Eligendi suscipit et numquam non.","description":"Maxime quaerat rerum tenetur itaque at ad quia."}],"created_at":"2024-06-27T19:09:49.000000Z","updated_at":"2024-06-27 19:09:49"},{"id":5,"title":"\u0428\u043f\u043e\u043d","order_position":0,"wrapper_variants":[{"uuid":"daa6946b-6dea-42bc-b7e0-412d12c470fe","image":"https:\/\/via.placeholder.com\/640x480.png\/00aaaa?text=tempora","title":"A error earum fugit fuga delectus.","description":"Nihil pariatur dolorum quia minima sint non."},{"uuid":"84e76d2c-2ee6-411f-b6eb-e6697d1499c2","image":"https:\/\/via.placeholder.com\/640x480.png\/0066bb?text=qui","title":"Voluptatem voluptatem quo quod.","description":"Dolore sed qui maxime dicta et maxime."},{"uuid":"9af9e802-9370-40a8-afde-b3e27b6a5df6","image":"https:\/\/via.placeholder.com\/640x480.png\/0011dd?text=iste","title":"Id praesentium est quaerat et qui porro enim.","description":"Dolores molestias neque quod vel."},{"uuid":"7d13446d-b787-4a5a-9d8f-660925477bfa","image":"https:\/\/via.placeholder.com\/640x480.png\/00cc99?text=ex","title":"Neque quam debitis aperiam illum aperiam.","description":"Molestiae nesciunt voluptas qui illo sed sint."},{"uuid":"734af262-0d7f-4c68-87e2-0aa56fe63b35","image":"https:\/\/via.placeholder.com\/640x480.png\/003377?text=exercitationem","title":"Porro maiores aut et iure temporibus.","description":"Corrupti consequatur ipsum iusto atque."},{"uuid":"936eca33-6222-41fe-8484-23052b8f9d22","image":"https:\/\/via.placeholder.com\/640x480.png\/009966?text=beatae","title":"Impedit quia deleniti dignissimos.","description":"Inventore ut ut quae ratione."},{"uuid":"4256819d-1e44-4e64-9f05-b380789b1bd4","image":"https:\/\/via.placeholder.com\/640x480.png\/00bb44?text=accusamus","title":"Ut vitae ut impedit beatae unde.","description":"Libero rerum non qui asperiores."},{"uuid":"5535877f-cbb1-43e0-b44b-2c367d30c984","image":"https:\/\/via.placeholder.com\/640x480.png\/00ee99?text=quaerat","title":"Nostrum doloremque quos quos repellat.","description":"Dolorum qui dicta facere."}],"door_variants":[{"uuid":"a6fabccb-b10f-44c3-a489-c78efbc049c4","image":"https:\/\/via.placeholder.com\/640x480.png\/0022ee?text=quia","title":"Labore qui odit aspernatur praesentium.","description":"Similique non necessitatibus nisi autem."},{"uuid":"684b64cb-20c7-43b3-b3fd-b87e244444b0","image":"https:\/\/via.placeholder.com\/640x480.png\/00bb22?text=eaque","title":"Itaque vero sed enim asperiores.","description":"Quo non id ipsum qui atque est voluptatibus et."},{"uuid":"9f395284-9016-4dd4-b94c-dbb1bb5f884e","image":"https:\/\/via.placeholder.com\/640x480.png\/002244?text=iusto","title":"Voluptatem et sint consequuntur exercitationem.","description":"Nisi ut in accusamus quo dolorum blanditiis quis."},{"uuid":"a7cebde7-c8ea-4345-8672-00475d24ccec","image":"https:\/\/via.placeholder.com\/640x480.png\/00eeee?text=optio","title":"Est sequi eligendi dicta aut ut cumque aut neque.","description":"Sed omnis vel optio accusantium."},{"uuid":"cd859632-8383-4b4b-aa9c-b33a1bafd58b","image":"https:\/\/via.placeholder.com\/640x480.png\/008833?text=et","title":"Modi ut quis nihil mollitia quisquam quae sit.","description":"Delectus unde et sint inventore."}],"created_at":"2024-06-27T19:09:49.000000Z","updated_at":"2024-06-27 19:09:49"},{"id":6,"title":"\u041c\u0443\u043b\u044c\u0442\u0438\u0448\u043f\u043e\u043d","order_position":0,"wrapper_variants":[{"uuid":"7d73cfd4-2de9-4158-a77b-6ee27a2314d2","image":"https:\/\/via.placeholder.com\/640x480.png\/0099ff?text=odit","title":"Eum ratione molestias minima ut quia.","description":"Temporibus et aliquid sed velit consequatur."},{"uuid":"0f00a761-071f-498c-81b9-6eaba566a9aa","image":"https:\/\/via.placeholder.com\/640x480.png\/00eecc?text=rerum","title":"Quod dolorem qui rerum aspernatur.","description":"Illo eius non quas quo voluptas aut illum."},{"uuid":"7323dbe4-7000-4cd9-b50b-702139419cd7","image":"https:\/\/via.placeholder.com\/640x480.png\/0022cc?text=architecto","title":"Et incidunt expedita quisquam tempora.","description":"Explicabo quod nemo possimus."},{"uuid":"fa6d455a-93c6-4329-bd3d-e78a126eb66a","image":"https:\/\/via.placeholder.com\/640x480.png\/000033?text=porro","title":"Nobis praesentium suscipit enim repellendus eius.","description":"Mollitia ipsa quae exercitationem."},{"uuid":"e37ef5b5-8584-4ce6-899c-18fa38ccf1cc","image":"https:\/\/via.placeholder.com\/640x480.png\/00aaaa?text=praesentium","title":"Rem quidem quo alias vel eaque alias perferendis.","description":"Qui nulla error non nisi animi."},{"uuid":"92099b31-c98b-427a-a531-dfef743edd91","image":"https:\/\/via.placeholder.com\/640x480.png\/00eeff?text=rerum","title":"Quis officiis vel recusandae.","description":"Non architecto necessitatibus dolor ut."},{"uuid":"5929442a-ab94-4ec2-9ef3-1c2f19891daa","image":"https:\/\/via.placeholder.com\/640x480.png\/00eecc?text=tempore","title":"Voluptates culpa non excepturi facere.","description":"Sit voluptatem error et reiciendis totam."}],"door_variants":[{"uuid":"7fe39b91-70f9-4b01-af57-de6cae993528","image":"https:\/\/via.placeholder.com\/640x480.png\/00eeaa?text=sapiente","title":"Doloremque ut dolorem non.","description":"Quisquam minima et velit sint sapiente minima."},{"uuid":"072467e1-0398-4c1a-b758-e4112c306d4c","image":"https:\/\/via.placeholder.com\/640x480.png\/003399?text=sint","title":"Quis voluptatem velit consectetur repudiandae.","description":"Reprehenderit nostrum est aut dolorem."},{"uuid":"bff15e24-ee4c-4739-b5df-5203f8a7bcdb","image":"https:\/\/via.placeholder.com\/640x480.png\/003366?text=minus","title":"Odio saepe quaerat sit optio.","description":"Et mollitia itaque in."},{"uuid":"a14fc9b2-76a1-4b3b-9df8-8cac76c90aaa","image":"https:\/\/via.placeholder.com\/640x480.png\/00cc33?text=blanditiis","title":"Autem placeat sit officiis dolor sunt placeat.","description":"Laboriosam quidem debitis aliquid in."},{"uuid":"ddf75584-3174-48a2-88d3-3088c8905680","image":"https:\/\/via.placeholder.com\/640x480.png\/006611?text=et","title":"Qui laborum ea enim voluptate.","description":"Et officia qui est eum nesciunt eligendi."},{"uuid":"748b3232-04c3-4a07-9496-9c6e5dcda21f","image":"https:\/\/via.placeholder.com\/640x480.png\/00aadd?text=debitis","title":"A quae voluptatum voluptatem modi et.","description":"Ut architecto sequi qui a eum ut."},{"uuid":"9c150f23-f9aa-4c4c-954d-4d797a5b1905","image":"https:\/\/via.placeholder.com\/640x480.png\/00aabb?text=voluptatem","title":"Nulla qui minus qui cupiditate.","description":"In ducimus sit illum impedit veniam."}],"created_at":"2024-06-27T19:09:49.000000Z","updated_at":"2024-06-27 19:09:49"},{"id":7,"title":"\u041d\u0430\u0442\u0443\u0440\u0430\u043b\u044c\u043d\u044b\u0439 \u0448\u043f\u043e\u043d","order_position":0,"wrapper_variants":[{"uuid":"49e813eb-d709-466a-aed2-70659005d187","image":"https:\/\/via.placeholder.com\/640x480.png\/001144?text=vel","title":"Et qui hic veritatis nihil numquam quo.","description":"Ex doloremque ipsam quibusdam et."},{"uuid":"20bcc8b5-6df9-4194-8c51-030b2c8297b5","image":"https:\/\/via.placeholder.com\/640x480.png\/004433?text=quia","title":"Maxime ipsam enim voluptatem id itaque repellat.","description":"Voluptas quos asperiores eius ut sit."},{"uuid":"fc59a4b6-2680-4c73-9c50-8b70f70678b2","image":"https:\/\/via.placeholder.com\/640x480.png\/00aabb?text=illum","title":"Dolor velit aliquid iste velit dolores.","description":"Qui voluptatem placeat saepe debitis."},{"uuid":"0513ec90-b588-4427-8228-61565cee6813","image":"https:\/\/via.placeholder.com\/640x480.png\/0011aa?text=sit","title":"Saepe eum rerum atque repellendus odio.","description":"Nihil quia autem a eaque et odio."},{"uuid":"ad6f2cc4-0c10-43a7-8e42-6f679926c130","image":"https:\/\/via.placeholder.com\/640x480.png\/009955?text=laudantium","title":"Voluptatum quod hic quod ab molestiae.","description":"Nemo vero et tenetur autem rem occaecati."},{"uuid":"710a9e81-929c-4c58-ba87-b2fd79eeb22b","image":"https:\/\/via.placeholder.com\/640x480.png\/0099bb?text=ea","title":"Modi eum commodi minima veniam provident neque.","description":"Repellat maiores sit deleniti."},{"uuid":"e01930d2-9fc3-482c-9c78-b05a8a0f98b7","image":"https:\/\/via.placeholder.com\/640x480.png\/001122?text=placeat","title":"Ut similique debitis veritatis recusandae facere.","description":"Qui ipsam quis voluptatum omnis nihil."},{"uuid":"90928fed-4462-43c0-8477-1e7a8b190220","image":"https:\/\/via.placeholder.com\/640x480.png\/0066ee?text=nesciunt","title":"Libero accusamus vitae est ut ea.","description":"Sit et perspiciatis explicabo vel voluptas."}],"door_variants":[{"uuid":"2548a6e7-5b63-4aba-b099-197e9f2bea97","image":"https:\/\/via.placeholder.com\/640x480.png\/009911?text=ut","title":"Quia magni aut aut minima ratione dolorum.","description":"Quisquam quas quas laborum quae."},{"uuid":"959fefb8-a421-46a2-a7ac-98087ff1f3d4","image":"https:\/\/via.placeholder.com\/640x480.png\/002244?text=doloremque","title":"Quis quisquam cumque dolore in omnis quis.","description":"Quia in aut fuga temporibus aut."},{"uuid":"a8a4988a-cde6-489c-9940-b51f1f9a949c","image":"https:\/\/via.placeholder.com\/640x480.png\/00cc11?text=ipsum","title":"Quis atque quos saepe nostrum adipisci.","description":"Pariatur rerum debitis qui porro dolorem."},{"uuid":"0cc14b03-4cdb-4d51-9a13-9afe40119947","image":"https:\/\/via.placeholder.com\/640x480.png\/0099ee?text=assumenda","title":"Labore incidunt asperiores dicta delectus hic ut.","description":"Enim et voluptatem maxime natus."},{"uuid":"f76f2b02-8d27-4d94-8851-b8d923f523cd","image":"https:\/\/via.placeholder.com\/640x480.png\/00ccee?text=aut","title":"Ut rem accusamus excepturi.","description":"Nostrum non quia natus id consequuntur."},{"uuid":"ea06b9f4-7537-4185-a174-f8b4c49c0710","image":"https:\/\/via.placeholder.com\/640x480.png\/005533?text=et","title":"Nostrum ipsa quas voluptatem aut iusto.","description":"Tenetur dolorem molestiae expedita."},{"uuid":"f329175a-1fe9-40b0-b32d-c445553e1e7c","image":"https:\/\/via.placeholder.com\/640x480.png\/00aaee?text=sit","title":"Aut quam similique veniam ut.","description":"Quam eius dolores porro quis illo ab sed."},{"uuid":"e31321f8-6536-47c4-ba49-d2f5579e6f0b","image":"https:\/\/via.placeholder.com\/640x480.png\/0011ff?text=ullam","title":"Sint quam vitae cumque exercitationem deserunt.","description":"Ut id facere et esse laborum a necessitatibus."},{"uuid":"bfa5b4ec-f9e4-4757-b657-afa7698a32d2","image":"https:\/\/via.placeholder.com\/640x480.png\/003366?text=molestiae","title":"Velit totam quos magnam unde debitis.","description":"Sed sed vero quis qui laudantium voluptatibus."}],"created_at":"2024-06-27T19:09:49.000000Z","updated_at":"2024-06-27 19:09:49"},{"id":8,"title":"\u042d\u043c\u0430\u043b\u044c","order_position":0,"wrapper_variants":[{"uuid":"5457865c-388a-45bd-b2a1-d3d0a801b09d","image":"https:\/\/via.placeholder.com\/640x480.png\/009911?text=possimus","title":"Laudantium id aut voluptatem qui sit eos et.","description":"Laborum officia atque dolore qui cum minus nulla."},{"uuid":"cb941a5c-1de9-4d94-b7f4-93e7e07ca13d","image":"https:\/\/via.placeholder.com\/640x480.png\/00aadd?text=illo","title":"Asperiores iste rerum voluptatem cupiditate et.","description":"Et id dolores et et adipisci velit."},{"uuid":"affb83a0-3eee-48a3-a757-34a3009b2435","image":"https:\/\/via.placeholder.com\/640x480.png\/005577?text=amet","title":"Aut praesentium omnis ratione maiores.","description":"Deleniti magni vero mollitia corrupti enim."},{"uuid":"93270814-9032-4355-be22-7220a7d57945","image":"https:\/\/via.placeholder.com\/640x480.png\/00dd66?text=beatae","title":"Repellat sed dolor quae veritatis laborum vel.","description":"Et aspernatur et numquam atque veritatis nulla."},{"uuid":"7b37c57a-2e45-4bb4-a782-ab4f77e7b33b","image":"https:\/\/via.placeholder.com\/640x480.png\/000011?text=et","title":"Velit officiis odio ab earum ut.","description":"Temporibus voluptas nulla nihil officia."}],"door_variants":[{"uuid":"59a7a7e8-0a4f-4270-bbc9-85b01316717b","image":"https:\/\/via.placeholder.com\/640x480.png\/00aabb?text=omnis","title":"Aliquid et iure error repudiandae.","description":"Est qui id sint dolorem."},{"uuid":"0f24e728-3f1b-4eb8-bcbe-a2d91ef1053f","image":"https:\/\/via.placeholder.com\/640x480.png\/0066dd?text=eveniet","title":"Dolores beatae molestias veniam.","description":"Sit assumenda in et eos numquam velit."},{"uuid":"668be173-a213-460f-a6c7-0c5a0d2efa17","image":"https:\/\/via.placeholder.com\/640x480.png\/0099aa?text=voluptatem","title":"Et id vel sit sunt libero quia molestiae soluta.","description":"Id molestias itaque ipsa unde omnis odio."},{"uuid":"03793737-98c1-4f4d-a3b4-813285eef736","image":"https:\/\/via.placeholder.com\/640x480.png\/0066bb?text=quis","title":"Nihil voluptatem sed vel minus magni in sint.","description":"Et at et aperiam consectetur consequatur."},{"uuid":"cbf5a149-6ce9-4c39-b41e-24dfe2e314b4","image":"https:\/\/via.placeholder.com\/640x480.png\/002200?text=aperiam","title":"Cum numquam laboriosam quia exercitationem.","description":"Labore sequi ducimus ipsa."}],"created_at":"2024-06-27T19:09:49.000000Z","updated_at":"2024-06-27 19:09:49"},{"id":9,"title":"\u0421\u0442\u0435\u043a\u043b\u043e","order_position":0,"wrapper_variants":[{"uuid":"b3c6c4e6-322e-4177-9dc3-1660405e99b2","image":"https:\/\/via.placeholder.com\/640x480.png\/00aa55?text=eius","title":"Totam culpa corporis excepturi in commodi eaque.","description":"Voluptatem ea quis dolores vel."},{"uuid":"d63fe211-91c7-40ef-87a4-e1373f2958ed","image":"https:\/\/via.placeholder.com\/640x480.png\/0022aa?text=et","title":"Omnis exercitationem ut modi fuga.","description":"Tenetur rerum possimus debitis vel debitis quia."},{"uuid":"54ff2388-c0a4-4ca5-b073-6ebabcfe6cda","image":"https:\/\/via.placeholder.com\/640x480.png\/005533?text=eligendi","title":"Qui quis corrupti qui quaerat ab est.","description":"Labore in sit adipisci corrupti."},{"uuid":"a19ac543-8ba5-4531-8e96-fb823024896e","image":"https:\/\/via.placeholder.com\/640x480.png\/00aa11?text=perspiciatis","title":"Animi quam tempora vero id.","description":"Impedit aut odio aspernatur aspernatur molestiae."},{"uuid":"f76f6475-65ef-4875-9bd9-c8e3991d22e6","image":"https:\/\/via.placeholder.com\/640x480.png\/00bb11?text=qui","title":"Laboriosam est nam assumenda est totam.","description":"Incidunt animi ipsa eius et non."},{"uuid":"f99843b1-8360-4c08-935a-f5b8b4920e8f","image":"https:\/\/via.placeholder.com\/640x480.png\/0099cc?text=nobis","title":"Maxime est rerum quia vel maxime.","description":"Et consequatur sed voluptas."},{"uuid":"64d2c076-409d-4997-b2ae-f797c32a8ee3","image":"https:\/\/via.placeholder.com\/640x480.png\/00aa33?text=eius","title":"Minima illo dignissimos ex non et aut hic.","description":"Corporis incidunt ullam omnis."},{"uuid":"205af31b-780d-4600-a7fa-0413ab06e370","image":"https:\/\/via.placeholder.com\/640x480.png\/002299?text=sunt","title":"Ut officiis voluptas velit vero fugiat natus.","description":"Velit ut sit natus harum magni."},{"uuid":"8a3460f7-9884-4a09-b580-f3af99ecc802","image":"https:\/\/via.placeholder.com\/640x480.png\/00eeee?text=sint","title":"Rerum velit mollitia libero ex.","description":"Distinctio esse odit ut fugiat est in culpa."}],"door_variants":[{"uuid":"83f066f3-57dd-47e8-8703-a89320878ad2","image":"https:\/\/via.placeholder.com\/640x480.png\/0055ee?text=rem","title":"Sunt temporibus sit nihil totam quis id.","description":"Sequi voluptas cum nesciunt id eum laborum quia."},{"uuid":"f56b9247-c36e-4f92-8494-9058e0def1f1","image":"https:\/\/via.placeholder.com\/640x480.png\/0044cc?text=occaecati","title":"Voluptatem quia ipsam ut ea.","description":"Veniam ducimus nostrum quam."},{"uuid":"141cc9f9-e1e0-49ff-b8d8-00ee3a4ff5bb","image":"https:\/\/via.placeholder.com\/640x480.png\/00ffbb?text=atque","title":"Vero aliquam doloribus voluptatem.","description":"Eveniet et tempore voluptas ea autem dolore."},{"uuid":"ce07db41-c2f3-45fe-8762-42d3b73d008a","image":"https:\/\/via.placeholder.com\/640x480.png\/0000cc?text=est","title":"Iure nulla qui molestiae dolor enim eum.","description":"Velit aut neque eum eaque ut."},{"uuid":"1a99d486-377b-471b-a248-4df3a5d0e361","image":"https:\/\/via.placeholder.com\/640x480.png\/00dddd?text=culpa","title":"Omnis sed sit enim eos dolorem minus.","description":"Nihil non a maxime consequatur mollitia porro."},{"uuid":"d999b3b5-c69a-4223-85ed-3bce57c29abe","image":"https:\/\/via.placeholder.com\/640x480.png\/004477?text=quia","title":"Sapiente laudantium praesentium voluptas et.","description":"Sed ut et doloremque quibusdam voluptate dolores."},{"uuid":"af889328-c597-4b6d-b3b0-6dba445c626a","image":"https:\/\/via.placeholder.com\/640x480.png\/00ccdd?text=soluta","title":"A dolor possimus nobis sit molestiae.","description":"Non voluptas dolor officiis et maiores impedit."},{"uuid":"34551d80-e706-47a4-a4c0-93e30fd12e09","image":"https:\/\/via.placeholder.com\/640x480.png\/00ccbb?text=recusandae","title":"Fuga aut blanditiis quis consectetur.","description":"Molestiae explicabo ea aut et."},{"uuid":"2f30f2e0-347f-48a2-9159-f9a9906c6653","image":"https:\/\/via.placeholder.com\/640x480.png\/00bbaa?text=fuga","title":"Est minus qui dolores dolorum.","description":"Enim minus accusamus dolorem eius libero earum."},{"uuid":"edf06f17-4de4-4ec6-8ac6-a29706b5239c","image":"https:\/\/via.placeholder.com\/640x480.png\/003355?text=corporis","title":"Quia incidunt aut animi facere.","description":"Explicabo aspernatur autem itaque ut sed."},{"uuid":"a496d567-f6c0-48e0-8d63-dde946903872","image":"https:\/\/via.placeholder.com\/640x480.png\/00ff77?text=doloribus","title":"Ut id exercitationem quod. Aut aut sed eligendi.","description":"Voluptatum adipisci iusto ea sit."}],"created_at":"2024-06-27T19:09:49.000000Z","updated_at":"2024-06-27 19:09:49"},{"id":10,"title":"\u0410\u041a\u0412\u0410","order_position":0,"wrapper_variants":[{"uuid":"ad42c4a3-6458-46ba-9a12-8c6915da0063","image":"https:\/\/via.placeholder.com\/640x480.png\/001199?text=rerum","title":"Et error ipsa et voluptatem sed ut dignissimos.","description":"Aspernatur totam quas dicta non."},{"uuid":"15374711-9192-442f-acc6-b8c7713f67e2","image":"https:\/\/via.placeholder.com\/640x480.png\/00dd22?text=itaque","title":"Sed ut saepe cupiditate non sit beatae.","description":"Accusamus voluptatibus laboriosam qui maxime."},{"uuid":"1de09627-0584-4466-9a9f-dacf01da5de4","image":"https:\/\/via.placeholder.com\/640x480.png\/008800?text=perspiciatis","title":"Voluptas illo veritatis error iusto.","description":"Voluptate maiores eligendi deserunt."},{"uuid":"54b03195-2937-4b84-a799-36f5ed164d2a","image":"https:\/\/via.placeholder.com\/640x480.png\/001166?text=cupiditate","title":"Maiores optio labore rerum.","description":"Aut alias deserunt enim aliquid non soluta ex."},{"uuid":"34a25e68-937e-4da6-87df-88486d42626c","image":"https:\/\/via.placeholder.com\/640x480.png\/009944?text=distinctio","title":"Totam ipsa tempore sit voluptate vel.","description":"Laboriosam sed esse ipsa nisi odit molestiae."},{"uuid":"d01a3401-232d-4a5c-8232-7e0954f9625b","image":"https:\/\/via.placeholder.com\/640x480.png\/00ff55?text=non","title":"Vero officiis dolorem inventore.","description":"Sunt sit doloribus consequatur vero porro est."},{"uuid":"5ab8d741-3e47-4ddb-804e-63178287afdd","image":"https:\/\/via.placeholder.com\/640x480.png\/00bbee?text=asperiores","title":"Non temporibus occaecati fugit atque eum qui.","description":"Quis nostrum cumque ea impedit."},{"uuid":"7fb585f5-18f9-499a-beba-b3e4dc8b38b1","image":"https:\/\/via.placeholder.com\/640x480.png\/006611?text=autem","title":"Et recusandae beatae rem. Atque quae modi sunt.","description":"Facere dolorem molestias explicabo tenetur."}],"door_variants":[{"uuid":"0bc1edf6-58b7-4913-b84c-e18caa01cb2e","image":"https:\/\/via.placeholder.com\/640x480.png\/00bbbb?text=non","title":"Et voluptatem omnis dolor porro atque.","description":"Similique asperiores hic aut."},{"uuid":"f509aea4-aafc-4ee1-9013-4af98d93f38e","image":"https:\/\/via.placeholder.com\/640x480.png\/00ffcc?text=provident","title":"Ut quo aliquam sapiente repellendus magni.","description":"Beatae atque quaerat placeat praesentium quis."},{"uuid":"87b15992-d235-40c0-8741-c59a364bf3ad","image":"https:\/\/via.placeholder.com\/640x480.png\/001100?text=sit","title":"Architecto est eum ut illum unde.","description":"Expedita voluptate sit fugiat."},{"uuid":"5e28017d-22d2-4f7e-8670-8d5104aadec0","image":"https:\/\/via.placeholder.com\/640x480.png\/004455?text=quas","title":"Aut minima consequatur expedita error velit quo.","description":"Voluptas qui sunt alias reprehenderit."},{"uuid":"9c13990f-7bfb-4c53-bf4b-05e251b67d2d","image":"https:\/\/via.placeholder.com\/640x480.png\/0000ee?text=corrupti","title":"Tempore dolorem non vel nam omnis.","description":"Explicabo voluptatum natus officiis dolore."},{"uuid":"8ad6e814-626c-4ee2-9760-6ee9474d423d","image":"https:\/\/via.placeholder.com\/640x480.png\/00bb44?text=sit","title":"Et delectus suscipit iusto est recusandae sed.","description":"Quae veritatis autem ut recusandae."},{"uuid":"199ca636-4424-491d-9593-f222a436735e","image":"https:\/\/via.placeholder.com\/640x480.png\/00bb22?text=expedita","title":"Autem odit quia quae ut.","description":"Est at saepe fugiat saepe id."}],"created_at":"2024-06-27T19:09:49.000000Z","updated_at":"2024-06-27 19:09:49"},{"id":11,"title":"\u0415\u0413\u0413\u0415\u0420","order_position":0,"wrapper_variants":[{"uuid":"2329b92e-18d4-4853-87fb-9f1ea4006095","image":"https:\/\/via.placeholder.com\/640x480.png\/00aa88?text=hic","title":"Alias culpa vero minima.","description":"Error est ipsam possimus quis molestiae."},{"uuid":"2baff3a3-8eb7-4743-8ae1-4b403547b583","image":"https:\/\/via.placeholder.com\/640x480.png\/0055dd?text=aut","title":"Enim enim voluptatibus maiores ut accusantium.","description":"Voluptates consectetur voluptates labore eaque."},{"uuid":"ec00fdea-a2da-453d-a2e3-cd8188581f6e","image":"https:\/\/via.placeholder.com\/640x480.png\/0088ee?text=a","title":"Ducimus corporis est natus dolorum natus.","description":"Ea error dolorum in et beatae dolor commodi."},{"uuid":"87ec19cd-08ec-45ec-8254-43af1f8e1afd","image":"https:\/\/via.placeholder.com\/640x480.png\/008899?text=ducimus","title":"Necessitatibus quia magnam vel dolorem.","description":"Animi deleniti aut ea facilis."},{"uuid":"4e2aa3e5-bdc7-42d0-bdc2-b5c4549b1e5d","image":"https:\/\/via.placeholder.com\/640x480.png\/0022dd?text=neque","title":"Eaque aut officiis nemo.","description":"Adipisci vero iure eum aliquid similique."},{"uuid":"4c523bf4-3c69-44d5-b22a-67f6655821b7","image":"https:\/\/via.placeholder.com\/640x480.png\/0000dd?text=quod","title":"Et qui soluta ea. Rerum minus aperiam ad autem.","description":"Aut qui iste voluptatem et."},{"uuid":"159370ab-c45e-4a48-948a-cb3c7a746b49","image":"https:\/\/via.placeholder.com\/640x480.png\/009911?text=voluptatem","title":"Sit quo ut qui tenetur voluptates fugiat.","description":"Quae eum natus ratione aut dolores modi."},{"uuid":"20f0f72a-5ef7-4804-b0af-94a62a2e3dea","image":"https:\/\/via.placeholder.com\/640x480.png\/0055cc?text=qui","title":"Beatae non eos omnis nobis.","description":"Facere omnis dolores voluptatibus et."},{"uuid":"311715dd-9ef6-428b-aa23-087b70c75746","image":"https:\/\/via.placeholder.com\/640x480.png\/00ff00?text=non","title":"Nihil qui voluptatem qui sed.","description":"Voluptas est totam ut aut in."},{"uuid":"7b8126a1-f4ea-4dde-9a3a-8d27617799eb","image":"https:\/\/via.placeholder.com\/640x480.png\/0066ee?text=eos","title":"Labore et occaecati ipsa et.","description":"Magnam nihil vel qui enim cupiditate."}],"door_variants":[{"uuid":"9c35cc2e-f4e9-47c1-8597-5f80780bce0c","image":"https:\/\/via.placeholder.com\/640x480.png\/0000cc?text=id","title":"Natus sint et autem unde rerum labore autem enim.","description":"Eum rerum laudantium omnis quas quae nam omnis."},{"uuid":"b3cf57bd-4c8a-4dc4-928d-f07ba299cbab","image":"https:\/\/via.placeholder.com\/640x480.png\/005533?text=enim","title":"Et ipsum aspernatur ullam perferendis deserunt.","description":"Temporibus velit et quisquam rerum omnis."},{"uuid":"472c1b8f-7627-4aca-9aef-4f8372f9b611","image":"https:\/\/via.placeholder.com\/640x480.png\/008844?text=ab","title":"Perspiciatis odio adipisci accusantium ad non.","description":"Id temporibus aspernatur et vel."},{"uuid":"1d45b8c4-e7b8-45df-9097-d9c119389392","image":"https:\/\/via.placeholder.com\/640x480.png\/0066cc?text=et","title":"Beatae cupiditate itaque harum commodi.","description":"Et enim quo nobis quo."},{"uuid":"914c81f9-8450-4bc7-81d2-f72ffe76e2d6","image":"https:\/\/via.placeholder.com\/640x480.png\/001111?text=dolorem","title":"Temporibus inventore expedita voluptatum.","description":"Tempora ratione minus recusandae corporis."},{"uuid":"318edf60-b3c9-4a56-a904-8e5cfb3f54bf","image":"https:\/\/via.placeholder.com\/640x480.png\/00ee22?text=incidunt","title":"Unde nobis totam perferendis maiores est ut sint.","description":"Beatae repudiandae qui quod fugiat quasi."},{"uuid":"d329e458-5337-4346-8898-9ad315c4a65a","image":"https:\/\/via.placeholder.com\/640x480.png\/00ffff?text=vero","title":"Ipsam architecto veniam unde sit sed.","description":"Assumenda sed ut quasi assumenda eaque."}],"created_at":"2024-06-27T19:09:49.000000Z","updated_at":"2024-06-27 19:09:49"},{"id":12,"title":"\u041e\u043f\u0442","order_position":0,"wrapper_variants":null,"door_variants":null,"created_at":"2024-06-29T01:49:23.000000Z","updated_at":"2024-06-29 01:49:23"},{"id":13,"title":"\u0414\u0438\u043b\u0435\u0440","order_position":0,"wrapper_variants":null,"door_variants":null,"created_at":"2024-06-29T01:49:23.000000Z","updated_at":"2024-06-29 01:49:23"},{"id":14,"title":"\u0420\u043e\u0437\u043d\u0438\u0446\u0430","order_position":0,"wrapper_variants":null,"door_variants":null,"created_at":"2024-06-29T01:49:23.000000Z","updated_at":"2024-06-29 01:49:23"},{"id":15,"title":"\u0421\u0435\u0431\u0435\u0441\u0442\u043e\u0438\u043c\u043e\u0441\u0442\u044c","order_position":0,"wrapper_variants":null,"door_variants":null,"created_at":"2024-06-29T01:49:23.000000Z","updated_at":"2024-06-29 01:49:23"},{"id":16,"title":"\u041a\u043e\u044d\u0444\u0444\u0438\u0446\u0438\u0435\u043d\u0442","order_position":0,"wrapper_variants":null,"door_variants":null,"created_at":"2024-06-29T01:49:23.000000Z","updated_at":"2024-06-29 01:49:23"},{"id":17,"title":"\u0427\u0438\u0441\u043b\u043e \u043f\u0435\u0442\u0435\u043b\u044c","order_position":0,"wrapper_variants":null,"door_variants":null,"created_at":"2024-06-29T01:50:57.000000Z","updated_at":"2024-06-29 01:50:57"}],"handles":[{"id":1,"title":"Veritatis eius reprehenderit quam fugiat.","order_position":0,"color":"#b4822d","price":826,"variants":[{"uuid":"63fd6327-2b75-4a05-98fd-dab94f244fd2","image":"https:\/\/via.placeholder.com\/640x480.png\/001100?text=est","title":"Vitae voluptates accusantium corporis sequi.","description":"Dolores iure et soluta ab pariatur vero."},{"uuid":"181d3ba3-6528-4449-ac2b-1035b1065b05","image":"https:\/\/via.placeholder.com\/640x480.png\/00ee99?text=nihil","title":"Debitis magni nihil tempora eaque dignissimos.","description":"Quaerat voluptatem earum quaerat aut."},{"uuid":"55c74cf1-fe4f-49b6-847c-15f5e54bed74","image":"https:\/\/via.placeholder.com\/640x480.png\/003377?text=minima","title":"Maxime voluptatem qui architecto quae voluptatem.","description":"Similique iste sit illo beatae et nam."},{"uuid":"484095fa-87c6-45c4-979f-96e6ae17e81d","image":"https:\/\/via.placeholder.com\/640x480.png\/0088bb?text=non","title":"Odio temporibus laboriosam a rerum aut qui optio.","description":"Quas voluptatem tempore ad perferendis eum."},{"uuid":"a3648a5b-dfae-411f-8431-10f2a209d4ac","image":"https:\/\/via.placeholder.com\/640x480.png\/001155?text=minima","title":"Natus sit fuga vero et sint iure repellendus.","description":"Rerum minima velit deserunt sed non."},{"uuid":"2cdbfe36-a474-4f0e-b7ab-e0c0872769d8","image":"https:\/\/via.placeholder.com\/640x480.png\/0099dd?text=est","title":"Nulla quis tempore aliquid possimus et delectus.","description":"A suscipit eveniet facilis sit autem ad."},{"uuid":"36443d5e-de69-47dc-9286-864dd3b593eb","image":"https:\/\/via.placeholder.com\/640x480.png\/00aa44?text=vero","title":"Nam ipsum commodi ut distinctio.","description":"Iste sint voluptatem iure iure."}],"created_at":"2024-06-27T19:09:58.000000Z","updated_at":"2024-06-27 19:09:58"},{"id":2,"title":"Hic officia sed non temporibus.","order_position":0,"color":"#bbf276","price":283,"variants":[{"uuid":"045e1c8f-bc82-4839-b764-eda024cfb5ff","image":"https:\/\/via.placeholder.com\/640x480.png\/003300?text=ducimus","title":"Nobis rerum ea quos sit iste sit eos libero.","description":"Atque et aliquam illo eos quis doloremque."},{"uuid":"d73244e4-d481-4b55-8790-85946b676523","image":"https:\/\/via.placeholder.com\/640x480.png\/00bb99?text=est","title":"Ut corrupti et qui minima temporibus.","description":"Accusantium et autem voluptatem est."},{"uuid":"eb50aac8-250d-4ad8-a588-6cdebde19794","image":"https:\/\/via.placeholder.com\/640x480.png\/000011?text=sapiente","title":"Et architecto expedita debitis quo.","description":"Repellendus molestias tempora dolores sit."},{"uuid":"9c47bbe7-247e-4083-8e61-02ecbb3fdcf4","image":"https:\/\/via.placeholder.com\/640x480.png\/0044ff?text=natus","title":"Odit nobis consequatur molestias alias eos.","description":"Illum qui ullam non et culpa nesciunt."},{"uuid":"3b8bb66d-2b8d-44c0-84dd-f2e681655ac0","image":"https:\/\/via.placeholder.com\/640x480.png\/008833?text=consectetur","title":"Necessitatibus sed ab dolores odit.","description":"Eum sit nam consectetur quasi atque quae."},{"uuid":"2ae9aec3-e9d3-4cf2-a159-b700cba2750f","image":"https:\/\/via.placeholder.com\/640x480.png\/0077bb?text=enim","title":"Id ducimus saepe tenetur vel quia ab.","description":"Voluptates voluptatem atque perferendis iure."},{"uuid":"29dbbf60-a606-4f34-a741-47091a5ddf08","image":"https:\/\/via.placeholder.com\/640x480.png\/007744?text=facere","title":"Maiores aut fuga quidem quos.","description":"Nihil et eligendi dolor rem vitae dolores."},{"uuid":"99a1c65a-e9ee-46e7-9534-d416dd348e72","image":"https:\/\/via.placeholder.com\/640x480.png\/00ff00?text=voluptatem","title":"Itaque non animi numquam ab asperiores vitae.","description":"Illo nostrum eligendi amet ab id hic hic."},{"uuid":"0c4a2340-093a-4f09-afd0-1483695a2fa8","image":"https:\/\/via.placeholder.com\/640x480.png\/001199?text=ut","title":"Unde eaque a incidunt harum et mollitia placeat.","description":"Accusamus odio magni nihil vel perspiciatis."}],"created_at":"2024-06-27T19:09:58.000000Z","updated_at":"2024-06-27 19:09:58"},{"id":3,"title":"Dolores aut distinctio dolor provident et iusto.","order_position":0,"color":"#dc2d4b","price":636,"variants":[{"uuid":"9dd2acd9-f0da-48dd-a17c-b4d831b01028","image":"https:\/\/via.placeholder.com\/640x480.png\/00bb55?text=eum","title":"Sed ullam voluptatem est quasi voluptas.","description":"Odio rerum ad natus modi nisi."},{"uuid":"92e62cfc-90ba-4c78-aef1-f58e9bd672eb","image":"https:\/\/via.placeholder.com\/640x480.png\/005544?text=omnis","title":"Quod aspernatur corrupti qui.","description":"Deleniti ipsa est vel enim."},{"uuid":"8e0675a5-b281-4646-913e-a6988e65b649","image":"https:\/\/via.placeholder.com\/640x480.png\/001122?text=qui","title":"Est necessitatibus atque aspernatur beatae.","description":"A qui praesentium et id adipisci omnis."},{"uuid":"4a96e060-287a-4b00-9810-53f85d30a874","image":"https:\/\/via.placeholder.com\/640x480.png\/00ffdd?text=est","title":"Assumenda dolor voluptatum ea dolore odit.","description":"Aspernatur aut sequi rerum omnis."}],"created_at":"2024-06-27T19:09:58.000000Z","updated_at":"2024-06-27 19:09:58"},{"id":4,"title":"Ullam suscipit voluptas dolor quaerat sed est.","order_position":0,"color":"#36bf97","price":147,"variants":[{"uuid":"ccbc2221-5d76-4b11-8395-065c22efd30c","image":"https:\/\/via.placeholder.com\/640x480.png\/0033bb?text=consequatur","title":"Suscipit odit dolorum ut dolore ipsam minus eum.","description":"Perspiciatis ut rerum cumque ratione et."},{"uuid":"32bda630-75be-48e3-a940-68bc09966706","image":"https:\/\/via.placeholder.com\/640x480.png\/00aa99?text=qui","title":"Accusamus voluptatem quae in dolorum recusandae.","description":"Ut illum dolorem deleniti neque quia qui ut."},{"uuid":"c2760597-2bb8-47a3-a76d-a51b14273722","image":"https:\/\/via.placeholder.com\/640x480.png\/00dd22?text=facilis","title":"Nemo quasi hic ea similique vitae.","description":"Expedita fugiat veniam aspernatur."}],"created_at":"2024-06-27T19:09:58.000000Z","updated_at":"2024-06-27 19:09:58"},{"id":5,"title":"Exercitationem hic et rerum reprehenderit.","order_position":0,"color":"#d8d5cd","price":206,"variants":[{"uuid":"3e86a2af-1a9c-4aec-b2ea-a97dc9f2223f","image":"https:\/\/via.placeholder.com\/640x480.png\/00aabb?text=autem","title":"Harum eos natus rerum quasi at excepturi.","description":"Nihil earum mollitia cum vero esse pariatur."},{"uuid":"88114f07-d9b8-4382-ae0d-2c4d643325f2","image":"https:\/\/via.placeholder.com\/640x480.png\/0055cc?text=iusto","title":"Sed non harum reiciendis omnis ut.","description":"In libero deserunt a delectus."},{"uuid":"8195962c-ce6d-4118-a96c-dcb6c6aea05c","image":"https:\/\/via.placeholder.com\/640x480.png\/00eeee?text=natus","title":"Recusandae quidem deleniti eos.","description":"Ut rerum omnis incidunt minima sed."}],"created_at":"2024-06-27T19:09:58.000000Z","updated_at":"2024-06-27 19:09:58"}],"hinges":[{"id":1,"title":"\u0421\u0442\u0430\u043d\u0434\u0430\u0440\u0442","order_position":0,"price":{"wholesale":0,"dealer":0,"retail":0,"cost":0},"created_at":"2024-06-27T19:09:58.000000Z","updated_at":"2024-06-27 19:09:58"},{"id":2,"title":"AGB","order_position":0,"price":{"wholesale":800,"dealer":800,"retail":800,"cost":800},"created_at":"2024-06-27T19:09:58.000000Z","updated_at":"2024-06-27 19:09:58"}],"door_variants":[{"id":1,"title":"\u041a\u043e\u043c\u043f\u043b\u0435\u043a\u0442 \u0434\u0432\u0435\u0440\u0438 \u0441\u043a\u0440\u044b\u0442\u043e\u0433\u043e \u043c\u043e\u043d\u0442\u0430\u0436\u0430","price":{"wholesale":100,"dealer":200,"retail":300,"cost":400},"created_at":"2024-06-27T19:09:58.000000Z","updated_at":"2024-06-27 19:09:58"},{"id":2,"title":"\u041a\u043e\u0440\u043e\u0431","price":{"wholesale":100,"dealer":200,"retail":300,"cost":400},"created_at":"2024-06-27T19:09:58.000000Z","updated_at":"2024-06-27 19:09:58"},{"id":3,"title":"\u0414\u0432\u0435\u0440\u044c Magic","price":{"wholesale":100,"dealer":200,"retail":300,"cost":400},"created_at":"2024-06-27T19:09:58.000000Z","updated_at":"2024-06-27 19:09:58"},{"id":4,"title":"\u041f\u043e\u043b\u043e\u0442\u043d\u043e","price":{"wholesale":100,"dealer":200,"retail":300,"cost":400},"created_at":"2024-06-27T19:09:58.000000Z","updated_at":"2024-06-27 19:09:58"}],"colors":[{"id":1,"title":"Gold","order_position":0,"type":"all","code":"#f10","assign_with_size":true,"created_at":"2024-06-27T19:57:28.000000Z","updated_at":"2024-06-27 19:57:28","sizes":[]},{"id":2,"title":"Black","order_position":0,"type":"all","code":"#000","assign_with_size":true,"created_at":"2024-06-27T19:57:28.000000Z","updated_at":"2024-06-27 19:57:28","sizes":[]},{"id":3,"title":"Silver","order_position":0,"type":"all","code":"#111","assign_with_size":true,"created_at":"2024-06-27T19:57:28.000000Z","updated_at":"2024-06-27 19:57:28","sizes":[]},{"id":4,"title":"RAL","order_position":0,"type":"all","code":null,"assign_with_size":true,"created_at":"2024-06-27T19:57:28.000000Z","updated_at":"2024-06-27 19:57:28","sizes":[]}]}